{
  "Name": "American Dad!",
  "Title": "A Little Extra Scratch",
  "Desc": "A CIA agent does anything to protect his homeland and family.",
  "StartTime": "2025-06-16T19:30:00+00:00",
  "EndTime": "2025-06-16T20:00:00+00:00",
  "IsBlackedOut": false,
  "GameId": null,
  "Images": [
    {
      "Type": "thumbnail",
      "Url": "https://images2.9c9media.com/image_asset/2025_6_2_87848e8e-5d26-48da-b776-213ababdc68f_jpg_960x540.jpg",
      "Width": 960,
      "Height": 540
    }
  ],
  "Duration": 30,
  "SeasonNo": 18,
  "EpisodeNumber": "21",
  "Qualifiers": [
    "cc",
    "dvs",
    "hd 1080i",
    "hdtv",
    "stereo"
  ],
  "Ratings": [],
  "ReleaseYear": "2023",
  "EntityType": "Episode",
  "SubType": "Series",
  "Genres": [
    "animated",
    "sitcom"
  ],
  "LongDescription": "A CIA agent does anything to protect his homeland and family.",
  "TopCast": [
    "seth macfarlane",
    "wendy schaal",
    "rachael macfarlane"
  ],
  "Directors": [
    "josue cervantes"
  ]
}