{
  "Name": "Question Period",
  "Title": "Question Period",
  "Desc": "Discussions with key players in Canadian politics.",
  "StartTime": "2025-06-15T15:00:00+00:00",
  "EndTime": "2025-06-15T16:00:00+00:00",
  "IsBlackedOut": false,
  "GameId": null,
  "Images": [
    {
      "Type": "thumbnail",
      "Url": "https://images2.9c9media.com/image_asset/2025_6_1_43d906e0-bfa4-4c25-bbf8-c7b6005e546b_jpg_3840x2160.jpg",
      "Width": 3840,
      "Height": 2160
    }
  ],
  "Duration": 60,
  "SeasonNo": null,
  "EpisodeNumber": "26",
  "Qualifiers": [
    "cc",
    "new",
    "stereo"
  ],
  "Ratings": [],
  "ReleaseYear": "2025",
  "EntityType": "Episode",
  "SubType": "Series",
  "Genres": [
    "public affairs",
    "newsmagazine"
  ],
  "LongDescription": "Discussions with key players in Canadian politics.",
  "TopCast": [
    "evan solomon"
  ],
  "Directors": []
}