{
  "channel_id": "yle-areena",
  "broadcast_date": "2025-06-14",
  "broadcast_time": "2025-06-14T10:00:00+03:00",
  "program_data": {
    "title": "Pyhtäältä Pöydältä 2025",
    "description": "Ylen yhteistyökumppanin tuottamaa sisältöä.\n\nPyhtäältä Pöydältä on yhteiskunnallinen keskustelutapahtuma. Toisen päivän keskustelut painottuvat ajankohtaisiin aiheisiin, historiaan ja kulttuuriin. Keskustelijat ovat maan eturivin asiantuntijoita, mutta ilmapiiri kotoisan intiimi.\n\nToimitusjohtaja Timo Toropainen, Eläkesäätiöyhdistys, yhteiskuntasuhdejohtaja Panu Laturi, Seurana, pääsihteeri Rosa Meriläinen, KULTA ry, toiminnanjohtaja Jari Jokinen, TEK, yrittäjä Marko Kulmala, Insano, ex-europarlamentaarikko Nils Torvalds, valokuvaaja Juha Metso, toimittaja Marjo Näkki, juontajat Jari Korkki, Jussi Lähde ja Sallamaari Muhonen.\n\n\nSuorana suomalaisilta – Direkt från finländarna esittelee Ylen yhteistyökumppaneiden tarjoamia sisältöjä eri puolilta Suomea. Ylen vastaava päätoimittaja on Panu Pokkinen. \n",
    "pointer": {
      "type": "program",
      "uri": "yleareena://items/1-74817392"
    },
    "labels": [
      {
        "type": "broadcastStartDate",
        "formatted": "10.00",
        "raw": "2025-06-14T10:00:00+03:00",
        "rawType": "date"
      },
      {
        "type": "broadcastEndDate",
        "raw": "2025-06-14T15:20:50+03:00",
        "rawType": "date"
      },
      {
        "type": "duration",
        "formatted": "5 h 20 min",
        "raw": "PT19250S",
        "rawType": "duration"
      },
      {
        "type": "ondemandStatus",
        "raw": "current"
      },
      {
        "type": "seriesLink",
        "pointer": {
          "uri": "yleareena://items/1-73155362"
        }
      },
      {
        "type": "broadcastStatus",
        "raw": "expired"
      },
      {
        "type": "broadcastServiceType",
        "raw": "OndemandService"
      },
      {
        "type": "region",
        "raw": "World"
      },
      {
        "type": "mediaType",
        "raw": "video"
      }
    ],
    "presentation": "scheduleCard",
    "controls": [
      {
        "type": "navigator",
        "destination": {
          "type": "player",
          "uri": "https://areena.api.yle.fi/v1/ui/players/1-74817392.json?language=fi&v=10&client=yle-areena-web",
          "authentication": [
            "yle-api"
          ]
        },
        "title": "Katso alusta",
        "backgroundColor": "#29CCDE"
      }
    ],
    "type": "card"
  }
}